<?xml version='1.0' encoding='utf-8'?>
<resampletssmap>
	<userproj userid = 'karttur' projectid = 'karttur' tractid= 'karttur' siteid = '*' plotid = '*' system = 'smap'></userproj>
	<period startyear = '2015' startmonth = '04' startday = '23' endyear = '2019' endmonth = '02' endday = '19' timestep='16D'></period>

	<process processid ='seasonfilltsSmap' dsversion = '1.3'>
		<parameters></parameters>
		<srcpath volume = "Pegasus6"></srcpath>
		<dstpath volume = "Pegasus6"></dstpath>
		<srccomp>
			<soil-moisture-avg-16d source = "SPL3SMP-E.002" product = "SPL3SMP-E" folder = "soil-moisture-avg-16d-fill" band = "soil-moisture-avg-16d" prefix = "soil-moisture-avg-16d" suffix = "002-wboadj">	
			</soil-moisture-avg-16d>
		</srccomp>
	</process>	

</resampletssmap>
